reps/__init__.py
reps/compat.py
reps/conf.py
reps/consts.py
reps/ioutils.py
reps/utils.py
reps/backends/__init__.py
reps/backends/git.py
reps/model/__init__.py
reps/model/git.py
reps/model/gitstrings.py
reps-0.5.10.data/scripts/re
reps-0.5.10.dist-info/LICENSE
reps-0.5.10.dist-info/METADATA
reps-0.5.10.dist-info/WHEEL
reps-0.5.10.dist-info/top_level.txt
reps-0.5.10.dist-info/RECORD
